{"@t":"2021-03-28T17:52:06.5847467Z","@mt":"{LogPrefix} Terminating {Immediate}","LogPrefix":"[ServerRegistration] ","Immediate":"","SourceContext":"Umbraco.Web.Scheduling.BackgroundTaskRunner","ProcessId":11272,"ProcessName":"w3wp","ThreadId":229,"AppDomainId":6,"AppDomainAppId":"LMW3SVC2ROOT","MachineName":"DESKTOP-0DVKECB","Log4NetLevel":"INFO "}
{"@t":"2021-03-28T17:52:06.5852155Z","@mt":"{LogPrefix} Terminating {Immediate}","LogPrefix":"[TempFileCleanup] ","Immediate":"","SourceContext":"Umbraco.Web.Scheduling.BackgroundTaskRunner","ProcessId":11272,"ProcessName":"w3wp","ThreadId":229,"AppDomainId":6,"AppDomainAppId":"LMW3SVC2ROOT","MachineName":"DESKTOP-0DVKECB","Log4NetLevel":"INFO "}
{"@t":"2021-03-28T17:52:06.5896798Z","@mt":"{LogPrefix} Terminating {Immediate}","LogPrefix":"[ScheduledPublishing] ","Immediate":"","SourceContext":"Umbraco.Web.Scheduling.BackgroundTaskRunner","ProcessId":11272,"ProcessName":"w3wp","ThreadId":229,"AppDomainId":6,"AppDomainAppId":"LMW3SVC2ROOT","MachineName":"DESKTOP-0DVKECB","Log4NetLevel":"INFO "}
{"@t":"2021-03-28T17:52:06.5896798Z","@mt":"{LogPrefix} Terminating {Immediate}","LogPrefix":"[Umbraco.Web.Scheduling.IBackgroundTask] ","Immediate":"","SourceContext":"Umbraco.Web.Scheduling.BackgroundTaskRunner","ProcessId":11272,"ProcessName":"w3wp","ThreadId":229,"AppDomainId":6,"AppDomainAppId":"LMW3SVC2ROOT","MachineName":"DESKTOP-0DVKECB","Log4NetLevel":"INFO "}
{"@t":"2021-03-28T17:52:06.5896798Z","@mt":"{LogPrefix} Terminating {Immediate}","LogPrefix":"[HealthCheckNotifier] ","Immediate":"","SourceContext":"Umbraco.Web.Scheduling.BackgroundTaskRunner","ProcessId":11272,"ProcessName":"w3wp","ThreadId":229,"AppDomainId":6,"AppDomainAppId":"LMW3SVC2ROOT","MachineName":"DESKTOP-0DVKECB","Log4NetLevel":"INFO "}
{"@t":"2021-03-28T17:52:06.5896798Z","@mt":"{LogPrefix} Terminating {Immediate}","LogPrefix":"[TelemetryReporter] ","Immediate":"","SourceContext":"Umbraco.Web.Scheduling.BackgroundTaskRunner","ProcessId":11272,"ProcessName":"w3wp","ThreadId":229,"AppDomainId":6,"AppDomainAppId":"LMW3SVC2ROOT","MachineName":"DESKTOP-0DVKECB","Log4NetLevel":"INFO "}
{"@t":"2021-03-28T17:52:06.5896798Z","@mt":"{LogPrefix} Terminating {Immediate}","LogPrefix":"[KeepAlive] ","Immediate":"","SourceContext":"Umbraco.Web.Scheduling.BackgroundTaskRunner","ProcessId":11272,"ProcessName":"w3wp","ThreadId":229,"AppDomainId":6,"AppDomainAppId":"LMW3SVC2ROOT","MachineName":"DESKTOP-0DVKECB","Log4NetLevel":"INFO "}
{"@t":"2021-03-28T17:52:06.5896798Z","@mt":"{LogPrefix} Terminating {Immediate}","LogPrefix":"[LogScrubber] ","Immediate":"","SourceContext":"Umbraco.Web.Scheduling.BackgroundTaskRunner","ProcessId":11272,"ProcessName":"w3wp","ThreadId":229,"AppDomainId":6,"AppDomainAppId":"LMW3SVC2ROOT","MachineName":"DESKTOP-0DVKECB","Log4NetLevel":"INFO "}
{"@t":"2021-03-28T17:52:06.5896798Z","@mt":"{LogPrefix} Terminating {Immediate}","LogPrefix":"[ScheduledTasks] ","Immediate":"","SourceContext":"Umbraco.Web.Scheduling.BackgroundTaskRunner","ProcessId":11272,"ProcessName":"w3wp","ThreadId":229,"AppDomainId":6,"AppDomainAppId":"LMW3SVC2ROOT","MachineName":"DESKTOP-0DVKECB","Log4NetLevel":"INFO "}
{"@t":"2021-03-28T17:52:06.6100157Z","@mt":"{LogPrefix} Canceling tasks","LogPrefix":"[Umbraco.Web.Scheduling.IBackgroundTask] ","SourceContext":"Umbraco.Web.Scheduling.BackgroundTaskRunner","ProcessId":11272,"ProcessName":"w3wp","ThreadId":67,"AppDomainId":6,"AppDomainAppId":"LMW3SVC2ROOT","MachineName":"DESKTOP-0DVKECB","Log4NetLevel":"INFO "}
{"@t":"2021-03-28T17:52:06.6105116Z","@mt":"Stopping ({SignalSource})","SignalSource":"environment","SourceContext":"Umbraco.Core.Runtime.MainDom","ProcessId":11272,"ProcessName":"w3wp","ThreadId":229,"AppDomainId":6,"AppDomainAppId":"LMW3SVC2ROOT","MachineName":"DESKTOP-0DVKECB","Log4NetLevel":"INFO "}
{"@t":"2021-03-28T17:52:06.6105116Z","@mt":"{LogPrefix} Canceling tasks","LogPrefix":"[ScheduledTasks] ","SourceContext":"Umbraco.Web.Scheduling.BackgroundTaskRunner","ProcessId":11272,"ProcessName":"w3wp","ThreadId":154,"AppDomainId":6,"AppDomainAppId":"LMW3SVC2ROOT","MachineName":"DESKTOP-0DVKECB","Log4NetLevel":"INFO "}
{"@t":"2021-03-28T17:52:06.6129916Z","@mt":"{LogPrefix} Canceling tasks","LogPrefix":"[TempFileCleanup] ","SourceContext":"Umbraco.Web.Scheduling.BackgroundTaskRunner","ProcessId":11272,"ProcessName":"w3wp","ThreadId":73,"AppDomainId":6,"AppDomainAppId":"LMW3SVC2ROOT","MachineName":"DESKTOP-0DVKECB","Log4NetLevel":"INFO "}
{"@t":"2021-03-28T17:52:06.6129916Z","@mt":"{LogPrefix} Canceling tasks","LogPrefix":"[LogScrubber] ","SourceContext":"Umbraco.Web.Scheduling.BackgroundTaskRunner","ProcessId":11272,"ProcessName":"w3wp","ThreadId":285,"AppDomainId":6,"AppDomainAppId":"LMW3SVC2ROOT","MachineName":"DESKTOP-0DVKECB","Log4NetLevel":"INFO "}
{"@t":"2021-03-28T17:52:06.6129916Z","@mt":"{LogPrefix} Canceling tasks","LogPrefix":"[ScheduledPublishing] ","SourceContext":"Umbraco.Web.Scheduling.BackgroundTaskRunner","ProcessId":11272,"ProcessName":"w3wp","ThreadId":262,"AppDomainId":6,"AppDomainAppId":"LMW3SVC2ROOT","MachineName":"DESKTOP-0DVKECB","Log4NetLevel":"INFO "}
{"@t":"2021-03-28T17:52:06.6134875Z","@mt":"{LogPrefix} Canceling tasks","LogPrefix":"[ServerRegistration] ","SourceContext":"Umbraco.Web.Scheduling.BackgroundTaskRunner","ProcessId":11272,"ProcessName":"w3wp","ThreadId":37,"AppDomainId":6,"AppDomainAppId":"LMW3SVC2ROOT","MachineName":"DESKTOP-0DVKECB","Log4NetLevel":"INFO "}
{"@t":"2021-03-28T17:52:06.6134875Z","@mt":"{LogPrefix} Canceling tasks","LogPrefix":"[KeepAlive] ","SourceContext":"Umbraco.Web.Scheduling.BackgroundTaskRunner","ProcessId":11272,"ProcessName":"w3wp","ThreadId":72,"AppDomainId":6,"AppDomainAppId":"LMW3SVC2ROOT","MachineName":"DESKTOP-0DVKECB","Log4NetLevel":"INFO "}
{"@t":"2021-03-28T17:52:06.6134875Z","@mt":"{LogPrefix} Tasks {TaskStatus}, terminated","LogPrefix":"[Umbraco.Web.Scheduling.IBackgroundTask] ","TaskStatus":"cancelled","SourceContext":"Umbraco.Web.Scheduling.BackgroundTaskRunner","ProcessId":11272,"ProcessName":"w3wp","ThreadId":67,"AppDomainId":6,"AppDomainAppId":"LMW3SVC2ROOT","MachineName":"DESKTOP-0DVKECB","Log4NetLevel":"INFO "}
{"@t":"2021-03-28T17:52:06.6139836Z","@mt":"{LogPrefix} Tasks {TaskStatus}, terminated","LogPrefix":"[KeepAlive] ","TaskStatus":"cancelled","SourceContext":"Umbraco.Web.Scheduling.BackgroundTaskRunner","ProcessId":11272,"ProcessName":"w3wp","ThreadId":72,"AppDomainId":6,"AppDomainAppId":"LMW3SVC2ROOT","MachineName":"DESKTOP-0DVKECB","Log4NetLevel":"INFO "}
{"@t":"2021-03-28T17:52:06.6139836Z","@mt":"{LogPrefix} Canceling tasks","LogPrefix":"[TelemetryReporter] ","SourceContext":"Umbraco.Web.Scheduling.BackgroundTaskRunner","ProcessId":11272,"ProcessName":"w3wp","ThreadId":298,"AppDomainId":6,"AppDomainAppId":"LMW3SVC2ROOT","MachineName":"DESKTOP-0DVKECB","Log4NetLevel":"INFO "}
{"@t":"2021-03-28T17:52:06.6139836Z","@mt":"{LogPrefix} Tasks {TaskStatus}, terminated","LogPrefix":"[TelemetryReporter] ","TaskStatus":"cancelled","SourceContext":"Umbraco.Web.Scheduling.BackgroundTaskRunner","ProcessId":11272,"ProcessName":"w3wp","ThreadId":298,"AppDomainId":6,"AppDomainAppId":"LMW3SVC2ROOT","MachineName":"DESKTOP-0DVKECB","Log4NetLevel":"INFO "}
{"@t":"2021-03-28T17:52:06.6139836Z","@mt":"{LogPrefix} Canceling tasks","LogPrefix":"[HealthCheckNotifier] ","SourceContext":"Umbraco.Web.Scheduling.BackgroundTaskRunner","ProcessId":11272,"ProcessName":"w3wp","ThreadId":305,"AppDomainId":6,"AppDomainAppId":"LMW3SVC2ROOT","MachineName":"DESKTOP-0DVKECB","Log4NetLevel":"INFO "}
{"@t":"2021-03-28T17:52:06.6139836Z","@mt":"{LogPrefix} Tasks {TaskStatus}, terminated","LogPrefix":"[HealthCheckNotifier] ","TaskStatus":"cancelled","SourceContext":"Umbraco.Web.Scheduling.BackgroundTaskRunner","ProcessId":11272,"ProcessName":"w3wp","ThreadId":305,"AppDomainId":6,"AppDomainAppId":"LMW3SVC2ROOT","MachineName":"DESKTOP-0DVKECB","Log4NetLevel":"INFO "}
{"@t":"2021-03-28T17:52:06.6139836Z","@mt":"{LogPrefix} Tasks {TaskStatus}, terminated","LogPrefix":"[ScheduledPublishing] ","TaskStatus":"cancelled","SourceContext":"Umbraco.Web.Scheduling.BackgroundTaskRunner","ProcessId":11272,"ProcessName":"w3wp","ThreadId":262,"AppDomainId":6,"AppDomainAppId":"LMW3SVC2ROOT","MachineName":"DESKTOP-0DVKECB","Log4NetLevel":"INFO "}
{"@t":"2021-03-28T17:52:06.6139836Z","@mt":"{LogPrefix} Tasks {TaskStatus}, terminated","LogPrefix":"[TempFileCleanup] ","TaskStatus":"cancelled","SourceContext":"Umbraco.Web.Scheduling.BackgroundTaskRunner","ProcessId":11272,"ProcessName":"w3wp","ThreadId":73,"AppDomainId":6,"AppDomainAppId":"LMW3SVC2ROOT","MachineName":"DESKTOP-0DVKECB","Log4NetLevel":"INFO "}
{"@t":"2021-03-28T17:52:06.6139836Z","@mt":"{LogPrefix} Tasks {TaskStatus}, terminated","LogPrefix":"[LogScrubber] ","TaskStatus":"cancelled","SourceContext":"Umbraco.Web.Scheduling.BackgroundTaskRunner","ProcessId":11272,"ProcessName":"w3wp","ThreadId":285,"AppDomainId":6,"AppDomainAppId":"LMW3SVC2ROOT","MachineName":"DESKTOP-0DVKECB","Log4NetLevel":"INFO "}
{"@t":"2021-03-28T17:52:06.6139836Z","@mt":"{LogPrefix} Tasks {TaskStatus}, terminated","LogPrefix":"[ServerRegistration] ","TaskStatus":"cancelled","SourceContext":"Umbraco.Web.Scheduling.BackgroundTaskRunner","ProcessId":11272,"ProcessName":"w3wp","ThreadId":37,"AppDomainId":6,"AppDomainAppId":"LMW3SVC2ROOT","MachineName":"DESKTOP-0DVKECB","Log4NetLevel":"INFO "}
{"@t":"2021-03-28T17:52:06.6144796Z","@mt":"{LogPrefix} Tasks {TaskStatus}, terminated","LogPrefix":"[ScheduledTasks] ","TaskStatus":"cancelled","SourceContext":"Umbraco.Web.Scheduling.BackgroundTaskRunner","ProcessId":11272,"ProcessName":"w3wp","ThreadId":154,"AppDomainId":6,"AppDomainAppId":"LMW3SVC2ROOT","MachineName":"DESKTOP-0DVKECB","Log4NetLevel":"INFO "}
{"@t":"2021-03-28T17:52:06.7389766Z","@mt":"Released from MainDom","SourceContext":"Umbraco.Web.PublishedCache.NuCache.PublishedSnapshotService","ProcessId":11272,"ProcessName":"w3wp","ThreadId":229,"AppDomainId":6,"AppDomainAppId":"LMW3SVC2ROOT","MachineName":"DESKTOP-0DVKECB","Log4NetLevel":"INFO "}
{"@t":"2021-03-28T17:52:06.7409903Z","@mt":"{StartMessage} [Timing {TimingId}]","StartMessage":"Examine shutting down","TimingId":"ecb0b3f","SourceContext":"Umbraco.Web.Search.ExamineComponent","ProcessId":11272,"ProcessName":"w3wp","ThreadId":229,"AppDomainId":6,"AppDomainAppId":"LMW3SVC2ROOT","MachineName":"DESKTOP-0DVKECB","Log4NetLevel":"INFO "}
{"@t":"2021-03-28T17:52:06.8428199Z","@mt":"{EndMessage} ({Duration}ms) [Timing {TimingId}]","EndMessage":"Completed.","Duration":101,"TimingId":"ecb0b3f","SourceContext":"Umbraco.Web.Search.ExamineComponent","ProcessId":11272,"ProcessName":"w3wp","ThreadId":229,"AppDomainId":6,"AppDomainAppId":"LMW3SVC2ROOT","MachineName":"DESKTOP-0DVKECB","Log4NetLevel":"INFO "}
{"@t":"2021-03-28T17:52:06.8453001Z","@mt":"Released ({SignalSource})","SignalSource":"environment","SourceContext":"Umbraco.Core.Runtime.MainDom","ProcessId":11272,"ProcessName":"w3wp","ThreadId":229,"AppDomainId":6,"AppDomainAppId":"LMW3SVC2ROOT","MachineName":"DESKTOP-0DVKECB","Log4NetLevel":"INFO "}
{"@t":"2021-03-28T17:52:06.8467874Z","@mt":"{LogPrefix} Terminating {Immediate}","LogPrefix":"[RebuildIndexesOnStartup] ","Immediate":"","SourceContext":"Umbraco.Web.Scheduling.BackgroundTaskRunner","ProcessId":11272,"ProcessName":"w3wp","ThreadId":229,"AppDomainId":6,"AppDomainAppId":"LMW3SVC2ROOT","MachineName":"DESKTOP-0DVKECB","Log4NetLevel":"INFO "}
{"@t":"2021-03-28T17:52:06.8467874Z","@mt":"{LogPrefix} Terminating {Immediate}","LogPrefix":"[ServerInstProcess] ","Immediate":"","SourceContext":"Umbraco.Web.Scheduling.BackgroundTaskRunner","ProcessId":11272,"ProcessName":"w3wp","ThreadId":229,"AppDomainId":6,"AppDomainAppId":"LMW3SVC2ROOT","MachineName":"DESKTOP-0DVKECB","Log4NetLevel":"INFO "}
{"@t":"2021-03-28T17:52:06.8467874Z","@mt":"{LogPrefix} Canceling tasks","LogPrefix":"[RebuildIndexesOnStartup] ","SourceContext":"Umbraco.Web.Scheduling.BackgroundTaskRunner","ProcessId":11272,"ProcessName":"w3wp","ThreadId":103,"AppDomainId":6,"AppDomainAppId":"LMW3SVC2ROOT","MachineName":"DESKTOP-0DVKECB","Log4NetLevel":"INFO "}
{"@t":"2021-03-28T17:52:06.8467874Z","@mt":"{LogPrefix} Tasks {TaskStatus}, terminated","LogPrefix":"[RebuildIndexesOnStartup] ","TaskStatus":"cancelled","SourceContext":"Umbraco.Web.Scheduling.BackgroundTaskRunner","ProcessId":11272,"ProcessName":"w3wp","ThreadId":103,"AppDomainId":6,"AppDomainAppId":"LMW3SVC2ROOT","MachineName":"DESKTOP-0DVKECB","Log4NetLevel":"INFO "}
{"@t":"2021-03-28T17:52:06.8467874Z","@mt":"{LogPrefix} Canceling tasks","LogPrefix":"[ServerInstProcess] ","SourceContext":"Umbraco.Web.Scheduling.BackgroundTaskRunner","ProcessId":11272,"ProcessName":"w3wp","ThreadId":298,"AppDomainId":6,"AppDomainAppId":"LMW3SVC2ROOT","MachineName":"DESKTOP-0DVKECB","Log4NetLevel":"INFO "}
{"@t":"2021-03-28T17:52:06.8467874Z","@mt":"{LogPrefix} Tasks {TaskStatus}, terminated","LogPrefix":"[ServerInstProcess] ","TaskStatus":"cancelled","SourceContext":"Umbraco.Web.Scheduling.BackgroundTaskRunner","ProcessId":11272,"ProcessName":"w3wp","ThreadId":298,"AppDomainId":6,"AppDomainAppId":"LMW3SVC2ROOT","MachineName":"DESKTOP-0DVKECB","Log4NetLevel":"INFO "}
{"@t":"2021-03-28T17:52:08.6146656Z","@mt":"{LogPrefix} Canceling tasks","LogPrefix":"[HealthCheckNotifier] ","SourceContext":"Umbraco.Web.Scheduling.BackgroundTaskRunner","ProcessId":11272,"ProcessName":"w3wp","ThreadId":282,"AppDomainId":6,"AppDomainAppId":"LMW3SVC2ROOT","MachineName":"DESKTOP-0DVKECB","Log4NetLevel":"INFO "}
{"@t":"2021-03-28T17:52:08.6146656Z","@mt":"{LogPrefix} Canceling tasks","LogPrefix":"[Umbraco.Web.Scheduling.IBackgroundTask] ","SourceContext":"Umbraco.Web.Scheduling.BackgroundTaskRunner","ProcessId":11272,"ProcessName":"w3wp","ThreadId":67,"AppDomainId":6,"AppDomainAppId":"LMW3SVC2ROOT","MachineName":"DESKTOP-0DVKECB","Log4NetLevel":"INFO "}
{"@t":"2021-03-28T17:52:08.6146656Z","@mt":"{LogPrefix} Canceling tasks","LogPrefix":"[TelemetryReporter] ","SourceContext":"Umbraco.Web.Scheduling.BackgroundTaskRunner","ProcessId":11272,"ProcessName":"w3wp","ThreadId":164,"AppDomainId":6,"AppDomainAppId":"LMW3SVC2ROOT","MachineName":"DESKTOP-0DVKECB","Log4NetLevel":"INFO "}
{"@t":"2021-03-28T17:52:08.6146656Z","@mt":"{LogPrefix} Canceling tasks","LogPrefix":"[LogScrubber] ","SourceContext":"Umbraco.Web.Scheduling.BackgroundTaskRunner","ProcessId":11272,"ProcessName":"w3wp","ThreadId":291,"AppDomainId":6,"AppDomainAppId":"LMW3SVC2ROOT","MachineName":"DESKTOP-0DVKECB","Log4NetLevel":"INFO "}
{"@t":"2021-03-28T17:52:08.6146656Z","@mt":"{LogPrefix} Canceling tasks","LogPrefix":"[KeepAlive] ","SourceContext":"Umbraco.Web.Scheduling.BackgroundTaskRunner","ProcessId":11272,"ProcessName":"w3wp","ThreadId":61,"AppDomainId":6,"AppDomainAppId":"LMW3SVC2ROOT","MachineName":"DESKTOP-0DVKECB","Log4NetLevel":"INFO "}
{"@t":"2021-03-28T17:52:08.6146656Z","@mt":"{LogPrefix} Canceling tasks","LogPrefix":"[TempFileCleanup] ","SourceContext":"Umbraco.Web.Scheduling.BackgroundTaskRunner","ProcessId":11272,"ProcessName":"w3wp","ThreadId":69,"AppDomainId":6,"AppDomainAppId":"LMW3SVC2ROOT","MachineName":"DESKTOP-0DVKECB","Log4NetLevel":"INFO "}
{"@t":"2021-03-28T17:52:08.6146656Z","@mt":"{LogPrefix} Canceling tasks","LogPrefix":"[ScheduledPublishing] ","SourceContext":"Umbraco.Web.Scheduling.BackgroundTaskRunner","ProcessId":11272,"ProcessName":"w3wp","ThreadId":100,"AppDomainId":6,"AppDomainAppId":"LMW3SVC2ROOT","MachineName":"DESKTOP-0DVKECB","Log4NetLevel":"INFO "}
{"@t":"2021-03-28T17:52:08.6146656Z","@mt":"{LogPrefix} Canceling tasks","LogPrefix":"[ServerRegistration] ","SourceContext":"Umbraco.Web.Scheduling.BackgroundTaskRunner","ProcessId":11272,"ProcessName":"w3wp","ThreadId":91,"AppDomainId":6,"AppDomainAppId":"LMW3SVC2ROOT","MachineName":"DESKTOP-0DVKECB","Log4NetLevel":"INFO "}
{"@t":"2021-03-28T17:52:08.6300433Z","@mt":"{LogPrefix} Canceling tasks","LogPrefix":"[ScheduledTasks] ","SourceContext":"Umbraco.Web.Scheduling.BackgroundTaskRunner","ProcessId":11272,"ProcessName":"w3wp","ThreadId":154,"AppDomainId":6,"AppDomainAppId":"LMW3SVC2ROOT","MachineName":"DESKTOP-0DVKECB","Log4NetLevel":"INFO "}
{"@t":"2021-03-28T17:52:08.8599727Z","@mt":"{LogPrefix} Canceling tasks","LogPrefix":"[ServerInstProcess] ","SourceContext":"Umbraco.Web.Scheduling.BackgroundTaskRunner","ProcessId":11272,"ProcessName":"w3wp","ThreadId":158,"AppDomainId":6,"AppDomainAppId":"LMW3SVC2ROOT","MachineName":"DESKTOP-0DVKECB","Log4NetLevel":"INFO "}
{"@t":"2021-03-28T17:52:08.8599727Z","@mt":"{LogPrefix} Canceling tasks","LogPrefix":"[RebuildIndexesOnStartup] ","SourceContext":"Umbraco.Web.Scheduling.BackgroundTaskRunner","ProcessId":11272,"ProcessName":"w3wp","ThreadId":103,"AppDomainId":6,"AppDomainAppId":"LMW3SVC2ROOT","MachineName":"DESKTOP-0DVKECB","Log4NetLevel":"INFO "}
{"@t":"2021-03-28T17:52:36.9526038Z","@mt":"Application shutdown. Details: {ShutdownReason}\r\n\r\n_shutDownMessage={ShutdownMessage}\r\n\r\n_shutDownStack={ShutdownStack}","ShutdownReason":"HostingEnvironment","ShutdownMessage":"HostingEnvironment initiated shutdown\r\nHostingEnvironment caused shutdown","ShutdownStack":"   at System.Environment.GetStackTrace(Exception e, Boolean needFileInfo)\r\n   at System.Environment.get_StackTrace()\r\n   at System.Web.Hosting.HostingEnvironment.InitiateShutdownInternal()\r\n   at System.Web.Hosting.HostingEnvironment.InitiateShutdownWithoutDemand()\r\n   at System.Web.Hosting.PipelineRuntime.StopProcessing()","SourceContext":"Umbraco.Web.UmbracoApplicationBase","ProcessId":11272,"ProcessName":"w3wp","ThreadId":262,"AppDomainId":6,"AppDomainAppId":"LMW3SVC2ROOT","MachineName":"DESKTOP-0DVKECB","Log4NetLevel":"INFO "}
